[
  { "name": "Yle TV1", "telsuId": "yle1", "xmltvId": "tv1.yle.fi", "orderNumber": 1 },
  { "name": "Yle TV2", "telsuId": "yle2", "xmltvId": "tv2.yle.fi", "orderNumber": 2 },
  { "name": "MTV3", "telsuId": "mtv3", "xmltvId": "mtv3.fi", "orderNumber": 3 },
  { "name": "Nelonen", "telsuId": "nelonen", "xmltvId": "nelonen.fi", "orderNumber": 4 },
  { "name": "Yle Teema & Fem", "telsuId": "ylefem", "xmltvId": "fem.yle.fi", "orderNumber": 5 },
  { "name": "Sub", "telsuId": "subtv", "xmltvId": "sub.fi", "orderNumber": 6 },
  { "name": "TV5", "telsuId": "viisi", "xmltvId": "tv5.fi", "orderNumber": 7 },
  { "name": "Liv", "telsuId": "liv", "xmltvId": "liv.nelonen.fi", "orderNumber": 8 },
  { "name": "Jim", "telsuId": "jim", "xmltvId": "jim.nelonen.fi", "orderNumber": 9 },
  { "name": "Kutonen", "telsuId": "kutonen", "xmltvId": "kutonen.fi", "orderNumber": 10 },
  { "name": "TLC", "telsuId": "tlc", "xmltvId": "tlc.discoverynetworks.fi", "orderNumber": 11 },
  { "name": "FOX", "telsuId": "fox", "xmltvId": "fox.fi", "orderNumber": 12 },
  { "name": "AVA", "telsuId": "mtv3ava", "xmltvId": "ava.mtv.fi", "orderNumber": 13 },
  { "name": "Hero", "telsuId": "hero", "xmltvId": "herotv.fi", "orderNumber": 14 },
  { "name": "AlfaTV", "telsuId": "alfatv", "xmltvId": "alfatv.fi", "orderNumber": 15 },
  { "name": "Frii", "telsuId": "frii", "xmltvId": "frii.sbs.fi", "orderNumber": 16 },
  { "name": "National Geographic Channel", "telsuId": "nationalgeo", "xmltvId": "natgeo.fi", "orderNumber": 17 }
]

